conciseSchedules/__init__.py
conciseSchedules-1.0.3.dist-info/LICENSE
conciseSchedules-1.0.3.dist-info/METADATA
conciseSchedules-1.0.3.dist-info/WHEEL
conciseSchedules-1.0.3.dist-info/top_level.txt
conciseSchedules-1.0.3.dist-info/RECORD
