Metadata-Version: 2.1
Name: conciseSchedules
Version: 1.0.3
Summary: A Concise Schedules module -- conciseSchedules for Python.
Home-page: https://github.com/chenxinqun/conciseSchedules
Author: ChenXinqun
Author-email: chenxinqun163@163.com
Maintainer: ChenXinqun <chenxinqun163@163.com>
Maintainer-email: chenxinqun163@163.com
License: Apache 2.0
Platform: UNKNOWN
Classifier: License :: OSI Approved :: Apache Software License
Classifier: Intended Audience :: Developers
Classifier: Programming Language :: Python
Classifier: Programming Language :: Python :: 3
Classifier: Programming Language :: Python :: 3.5
Classifier: Programming Language :: Python :: 3.6
Classifier: Programming Language :: Python :: 3.7
Classifier: Programming Language :: Python :: Implementation :: CPython
Classifier: Development Status :: 5 - Production/Stable
Classifier: Operating System :: POSIX
Classifier: Operating System :: MacOS :: MacOS X
Classifier: Operating System :: Microsoft :: Windows
Classifier: Topic :: Internet :: WWW/HTTP
Classifier: Topic :: Software Development :: Libraries :: Application Frameworks
Classifier: Topic :: Software Development :: Libraries :: Python Modules
Classifier: Framework :: AsyncIO
Requires-Python: >=3.5.0
Requires-Dist: pytz
Requires-Dist: tzlocal
